{"is_source_file": true, "format": "Python", "description": "This file defines marshmallow schema for serializing and deserializing the Event model in the backend API.", "external_files": ["marshmallow", "marshmallow.fields", "marshmallow.validate"], "external_methods": [], "published": ["EventSchema"], "classes": [{"name": "EventSchema", "description": "Schema for serializing/deserializing Event model."}], "methods": [], "calls": ["fields.Int", "fields.Str", "fields.DateTime", "validate.Length"], "search-terms": ["EventSchema", "marshmallow schema", "serialization", "deserialization", "event model"], "state": 2, "file_id": 8, "knowledge_revision": 17, "git_revision": "", "ctags": [{"_type": "tag", "name": "EventSchema", "path": "/home/kavia/workspace/code-generation/event-management-api-54af4371/event_api_backend/app/schemas.py", "pattern": "/^class EventSchema(Schema):$/", "language": "Python", "kind": "class"}, {"_type": "tag", "name": "created_at", "path": "/home/kavia/workspace/code-generation/event-management-api-54af4371/event_api_backend/app/schemas.py", "pattern": "/^    created_at = fields.DateTime(dump_only=True, description=\"Creation timestamp\")$/", "language": "Python", "kind": "variable", "scope": "EventSchema", "scopeKind": "class"}, {"_type": "tag", "name": "description", "path": "/home/kavia/workspace/code-generation/event-management-api-54af4371/event_api_backend/app/schemas.py", "pattern": "/^    description = fields.Str(missing=None, allow_none=True, description=\"Description of the even/", "language": "Python", "kind": "variable", "scope": "EventSchema", "scopeKind": "class"}, {"_type": "tag", "name": "end_time", "path": "/home/kavia/workspace/code-generation/event-management-api-54af4371/event_api_backend/app/schemas.py", "pattern": "/^    end_time = fields.DateTime(required=True, description=\"Event end time (ISO format)\")$/", "language": "Python", "kind": "variable", "scope": "EventSchema", "scopeKind": "class"}, {"_type": "tag", "name": "id", "path": "/home/kavia/workspace/code-generation/event-management-api-54af4371/event_api_backend/app/schemas.py", "pattern": "/^    id = fields.Int(dump_only=True, description=\"Event ID\")$/", "language": "Python", "kind": "variable", "scope": "EventSchema", "scopeKind": "class"}, {"_type": "tag", "name": "location", "path": "/home/kavia/workspace/code-generation/event-management-api-54af4371/event_api_backend/app/schemas.py", "pattern": "/^    location = fields.Str(missing=None, allow_none=True, description=\"Event Location\")$/", "language": "Python", "kind": "variable", "scope": "EventSchema", "scopeKind": "class"}, {"_type": "tag", "name": "start_time", "path": "/home/kavia/workspace/code-generation/event-management-api-54af4371/event_api_backend/app/schemas.py", "pattern": "/^    start_time = fields.DateTime(required=True, description=\"Event start time (ISO format)\")$/", "language": "Python", "kind": "variable", "scope": "EventSchema", "scopeKind": "class"}, {"_type": "tag", "name": "title", "path": "/home/kavia/workspace/code-generation/event-management-api-54af4371/event_api_backend/app/schemas.py", "pattern": "/^    title = fields.Str(required=True, validate=validate.Length(min=1), description=\"Title of the/", "language": "Python", "kind": "variable", "scope": "EventSchema", "scopeKind": "class"}, {"_type": "tag", "name": "updated_at", "path": "/home/kavia/workspace/code-generation/event-management-api-54af4371/event_api_backend/app/schemas.py", "pattern": "/^    updated_at = fields.DateTime(dump_only=True, description=\"Last updated timestamp\")$/", "language": "Python", "kind": "variable", "scope": "EventSchema", "scopeKind": "class"}], "hash": "55531803923977f5f729b4c84bd3248f", "format-version": 4, "code-base-name": "event_api_backend", "filename": "event_api_backend/app/schemas.py", "fields": [{"name": "created_at = fields.DateTime(dump_only=True, description=\"Creation timestamp\")", "scope": "EventSchema", "scopeKind": "class", "description": "unavailable"}, {"name": "description = fields.Str(missing=None, allow_none=True, description=\"Description of the even/", "scope": "EventSchema", "scopeKind": "class", "description": "unavailable"}, {"name": "end_time = fields.DateTime(required=True, description=\"Event end time (ISO format)\")", "scope": "EventSchema", "scopeKind": "class", "description": "unavailable"}, {"name": "id = fields.Int(dump_only=True, description=\"Event ID\")", "scope": "EventSchema", "scopeKind": "class", "description": "unavailable"}, {"name": "location = fields.Str(missing=None, allow_none=True, description=\"Event Location\")", "scope": "EventSchema", "scopeKind": "class", "description": "unavailable"}, {"name": "start_time = fields.DateTime(required=True, description=\"Event start time (ISO format)\")", "scope": "EventSchema", "scopeKind": "class", "description": "unavailable"}, {"name": "title = fields.Str(required=True, validate=validate.Length(min=1), description=\"Title of the/", "scope": "EventSchema", "scopeKind": "class", "description": "unavailable"}, {"name": "updated_at = fields.DateTime(dump_only=True, description=\"Last updated timestamp\")", "scope": "EventSchema", "scopeKind": "class", "description": "unavailable"}], "revision_history": [{"17": ""}]}